evdsts/__init__.py
evdsts/base/__init__.py
evdsts/base/connecting.py
evdsts/base/indexing.py
evdsts/base/modelling.py
evdsts/base/searching.py
evdsts/base/transforming.py
evdsts/configuration/__init__.py
evdsts/configuration/cfg.py
evdsts/configuration/exceptions.py
evdsts/configuration/globals.py
evdsts/configuration/types.py
evdsts/data/__init__.py
evdsts/data/evds_index_en.json
evdsts/data/evds_index_tr.json
evdsts/utils/__init__.py
evdsts/utils/general.py
evdsts/utils/time_series.py
evdsts-1.0rc6.dist-info/METADATA
evdsts-1.0rc6.dist-info/WHEEL
evdsts-1.0rc6.dist-info/licenses/LICENSE.txt
evdsts-1.0rc6.dist-info/RECORD
