Metadata-Version: 2.4
Name: evdsts
Version: 1.0rc6
Summary: A Python implementation for retrieving and transforming macroeconomic time series data from TCMB EVDS (CBRT EDDS) API.
Project-URL: Homepage, https://github.com/syncoding/evdsts
Project-URL: Documentation, https://github.com/syncoding/evdsts/blob/master/README_EN.md
Project-URL: Repository, https://github.com/syncoding/evdsts.git
Project-URL: Issues, https://github.com/syncoding/evdsts/issues
Project-URL: Changelog, https://github.com/syncoding/evdsts/blob/master/CHANGELOG.md
Author-email: Burak CELIK <synertic@gmail.com>
Maintainer-email: syncoding <synertic@gmail.com>
License-Expression: MIT
License-File: LICENSE.txt
Keywords: cbot,econometrics,edds,evds,macroeconomics,tcmb
Classifier: Development Status :: 5 - Production/Stable
Classifier: Intended Audience :: Developers
Classifier: Intended Audience :: Financial and Insurance Industry
Classifier: Intended Audience :: Science/Research
Classifier: License :: OSI Approved :: MIT License
Classifier: Natural Language :: English
Classifier: Natural Language :: Turkish
Classifier: Operating System :: OS Independent
Classifier: Programming Language :: Python :: 3 :: Only
Classifier: Programming Language :: Python :: 3.11
Classifier: Programming Language :: Python :: 3.12
Classifier: Programming Language :: Python :: 3.13
Requires-Python: >=3.11
Requires-Dist: pandas>=2.0.0
Requires-Dist: requests>=2.12.5
Provides-Extra: excel
Requires-Dist: openpyxl; extra == 'excel'
